webrecon/__init__.py
webrecon/gcse.py
webrecon-0.0.2.dist-info/LICENSE
webrecon-0.0.2.dist-info/METADATA
webrecon-0.0.2.dist-info/WHEEL
webrecon-0.0.2.dist-info/top_level.txt
webrecon-0.0.2.dist-info/RECORD
