Metadata-Version: 2.1
Name: webrecon
Version: 0.0.2
Summary: Get information from various web resources
Home-page: https://github.com/adam-phillipps/recon/tree/master/web_recon
Author: Adam Phillipps
Author-email: adam.phillipps@gmail.com
License: UNKNOWN
Platform: UNKNOWN
Classifier: Programming Language :: Python :: 3
Classifier: License :: OSI Approved :: MIT License
Classifier: Operating System :: OS Independent
Requires-Dist: boto3
Requires-Dist: google-api-python-client
